contraptions/__init__.py
contraptions/math.py
contraptions/strings.py
contraptions-3.10.3.dist-info/AUTHORS.rst
contraptions-3.10.3.dist-info/LICENSE
contraptions-3.10.3.dist-info/METADATA
contraptions-3.10.3.dist-info/WHEEL
contraptions-3.10.3.dist-info/top_level.txt
contraptions-3.10.3.dist-info/RECORD
