Metadata-Version: 2.1
Name: contraptions
Version: 3.10.3
Summary: Contraptions is a collection of algorithms and utilities used in my personal py-projects.
Home-page: https://github.com/RyanFleck/contraptions
Author: Ryan Fleck
Author-email: Ryan.Fleck@protonmail.com
License: GNU General Public License v3
Keywords: contraptions
Platform: UNKNOWN
Classifier: Development Status :: 2 - Pre-Alpha
Classifier: Intended Audience :: Developers
Classifier: License :: OSI Approved :: GNU General Public License v3 (GPLv3)
Classifier: Natural Language :: English
Classifier: Programming Language :: Python :: 3
Classifier: Programming Language :: Python :: 3.5
Classifier: Programming Language :: Python :: 3.6
Classifier: Programming Language :: Python :: 3.7
Classifier: Programming Language :: Python :: 3.8
Requires-Python: >=3.5
